{
  "configs": [
    {
      "types": {
        "message": [
          {
            "name": "Chat",
            "conditions": [],
            "outcomes": [
              {
                "command": "/tellraw $playerName [\"\",{\"text\":\"[Twitch]\",\"bold\":true,\"color\":\"dark_purple\"},{\"text\":\" \",\"bold\":true},{\"text\":\"$display-name: $message\"}]",
                "type": "command"
              }
            ],
            "allowsOtherEventsToTrigger": true
          },
          {
            "name": "Kitta",
            "conditions": [
              {
                "phrase": "spawn",
                "type": "message"
              },
              {
                "username": "quirkygeek17",
                "type": "user"
              }
            ],
            "outcomes": [
              {
                "command": "/summon minecraft:skeleton ~ ~1 ~ {Health:20,Attributes:[{Name:\"generic.maxHealth\",Base:20}],Silent:1,HandItems:[{id:\"minecraft:bow\",tag:{display:{Name:\"Tarill's Present\",Lore:[\"====================\",\"Quirky's Special bow\",\"for tarill\",\"====================\"]},ench:[{id:51,lvl:1}]},Count:1},{}],HandDropChances:[2F,0F],ArmorItems:[{tag:{ench:[{id:8,lvl:3},{id:34,lvl:3}],display:{color:9312416}},id:\"minecraft:leather_boots\",Count:1},{tag:{ench:[{id:34,lvl:3}],display:{color:9312416}},id:\"minecraft:leather_leggings\",Count:1},{tag:{ench:[{id:34,lvl:3}],display:{color:9312416}},id:\"minecraft:leather_chestplate\",Count:1},{id:\"minecraft:skull\",Damage:3,Count:1,tag:{display:{Name:\"QuirkyGeek17 \"}}}],ArmorDropChances:[0F,0F,0F,2F],ActiveEffects:[{Id:24,Amplifier:9,Duration:2147483647}]}",
                "type": "command",
                "weight": 10
              },
              {
                "command": "/summon minecraft:zombie ~ ~1 ~ {Health:20,Attributes:[{Name:\"generic.maxHealth\",Base:20}],Silent:1,HandItems:[{id:\"minecraft:golden_sword\",tag:{display:{Name:\"Poking stick\",Lore:[\"=====================\",\"Quirky's Poking stick\",\"for tarill\",\"=====================\"]},ench:[{id:16,lvl:1}]},Count:1},{}],HandDropChances:[2F,0F],ArmorItems:[{tag:{ench:[{id:8,lvl:3},{id:34,lvl:3}],display:{color:9312416}},id:\"minecraft:leather_boots\",Count:1},{tag:{ench:[{id:34,lvl:3}],display:{color:9312416}},id:\"minecraft:leather_leggings\",Count:1},{tag:{ench:[{id:34,lvl:3}],display:{color:9312416}},id:\"minecraft:leather_chestplate\",Count:1},{id:\"minecraft:skull\",Damage:3,Count:1,tag:{display:{Name:\"QuirkyGeek17 \"}}}],ArmorDropChances:[0F,0F,0F,2F],ActiveEffects:[{Id:24,Amplifier:9,Duration:2147483647}]}",
                "type": "command",
                "weight": 10
              }
            ],
            "allowsOtherEventsToTrigger": true,
            "delay": 200,
            "cooldown": 600
          },
          {
            "name": "Battery trolls",
            "conditions": [
              {
                "username": "battery3996",
                "type": "user"
              }
            ],
            "outcomes": [
              {
                "command": "/give $playerName birdsfoods:pizza_supreme 1 0 {display:{Name:\"Special Pizza\"}}",
                "type": "command",
                "weight": 50
              },
              {
                "command": "/give $playerName birdsfoods:meat_pizza 1 0 {display:{Name:\"Special Pizza\"}}",
                "type": "command",
                "weight": 50
              },
              {
                "command": "/give $playerName birdsfoods:veg_pizza 1 0 {display:{Name:\"Special Pizza\"}}",
                "type": "command",
                "weight": 50
              }
            ],
            "allowsOtherEventsToTrigger": true,
            "delay": 200,
            "cooldown": 600
          },
          {
            "name": "boops NONDAMAGE",
            "conditions": [
              {
                "phrase": "boop",
                "type": "message"
              }
            ],
            "outcomes": [
              {
                "clientSide": true,
                "sound": "minecraft:entity.player.hurt",
                "target": "$player",
                "volume": 100.0,
                "type": "sound"
              }
            ],
            "allowsOtherEventsToTrigger": true,
            "cooldown": 200
          },
          {
            "name": "boops2 NONDAMAGE",
            "conditions": [
              {
                "phrase": "poke",
                "type": "message"
              }
            ],
            "outcomes": [
              {
                "clientSide": true,
                "sound": "minecraft:entity.player.hurt",
                "target": "$player",
                "volume": 100.0,
                "type": "sound"
              }
            ],
            "allowsOtherEventsToTrigger": true,
            "cooldown": 200
          },
          {
            "name": "CCI Reload",
            "conditions": [
              {
                "username": "battery3996",
                "type": "user"
              },
              {
                "phrase": "!reload",
                "type": "message"
              }
            ],
            "outcomes": [
              {
                "command": "/cci reload",
                "executeAsSelf": true,
                "type": "command"
              },
              {
                "command": "/tellraw $playerName [\"\",{\"text\":\"================================\",\"bold\":true,\"color\":\"gold\"},{\"text\":\"\\n\"},{\"text\":\"CCI Configs Reloaded! Enjoy!\",\"color\":\"yellow\"},{\"text\":\"\\n\"},{\"text\":\"================================\",\"bold\":true,\"color\":\"gold\"}]",
                "type": "command"
              }
            ]
          }
        ],
        "action": [
          {
            "name": "Action Chat",
            "conditions": [],
            "outcomes": [
              {
                "command": "/tellraw $playerName [\"\",{\"text\":\"[Twitch]\",\"bold\":true,\"color\":\"dark_purple\"},{\"text\":\" \",\"bold\":true},{\"text\":\"*\",\"bold\":true,\"color\":\"gold\"},{\"text\":\"$display-name $message\",\"color\":\"gold\"}]",
                "type": "command"
              }
            ],
            "allowsOtherEventsToTrigger": true
          },
          {
            "name": "in chat commands (WIP)",
            "conditions": [
              {
                "username": "battery3996",
                "type": "user"
              }
            ],
            "outcomes": [
              {
                "command": "/$message",
                "type": "command"
              }
            ],
            "allowsOtherEventsToTrigger": true
          },
          {
            "name": "Going up",
            "conditions": [
              {
                "phrase": "up",
                "type": "message"
              }
            ],
            "outcomes": [
              {
                "command": "/effect $playerName minecraft:levitation 4 1 true",
                "type": "command"
              }
            ],
            "allowsOtherEventsToTrigger": true,
            "delay": 300,
            "cooldown": 2400
          }
        ]
      }
    }
  ],
  "init": [],
  "type": "chat"
}